napari_cryofibsem_monitor/__init__.py
napari_cryofibsem_monitor/_dock_widget.py
napari_cryofibsem_monitor/napari.yaml
napari_cryofibsem_monitor/_tests/__init__.py
napari_cryofibsem_monitor/_tests/test_dock_widget.py
napari_cryofibsem_monitor/_tests/test_function.py
napari_cryofibsem_monitor-0.0.3.dist-info/LICENSE
napari_cryofibsem_monitor-0.0.3.dist-info/METADATA
napari_cryofibsem_monitor-0.0.3.dist-info/WHEEL
napari_cryofibsem_monitor-0.0.3.dist-info/entry_points.txt
napari_cryofibsem_monitor-0.0.3.dist-info/top_level.txt
napari_cryofibsem_monitor-0.0.3.dist-info/RECORD
