Metadata-Version: 2.1
Name: napari-cryofibsem-monitor
Version: 0.0.3
Summary: A plugin to monitor the creation of lamella using AutoTEM on a TFS Acquilos instrument
Home-page: https://github.com/jojoelfe/napari-cryofibsem-monitor
Author: Johannes Elferich
Author-email: jojotux123@hotmail.com
License: MIT
Project-URL: Bug Tracker, https://github.com/jojoelfe/napari-cryofibsem-monitor/issues
Project-URL: Documentation, https://github.com/jojoelfe/napari-cryofibsem-monitor#README.md
Project-URL: Source Code, https://github.com/jojoelfe/napari-cryofibsem-monitor
Project-URL: User Support, https://github.com/jojoelfe/napari-cryofibsem-monitor/issues
Classifier: Development Status :: 2 - Pre-Alpha
Classifier: Intended Audience :: Developers
Classifier: Framework :: napari
Classifier: Topic :: Software Development :: Testing
Classifier: Programming Language :: Python
Classifier: Programming Language :: Python :: 3
Classifier: Programming Language :: Python :: 3.7
Classifier: Programming Language :: Python :: 3.8
Classifier: Programming Language :: Python :: 3.9
Classifier: Operating System :: OS Independent
Classifier: License :: OSI Approved :: MIT License
Requires-Python: >=3.7
License-File: LICENSE
Requires-Dist: napari-plugin-engine (>=0.1.4)
Requires-Dist: numpy
Requires-Dist: tifffile
Requires-Dist: imreg-dft
Requires-Dist: matplotlib
